agentbase/__init__.py
agentbase/cli.py
agentbase/agents/base.py
agentbase/agents/runner.py
agentbase/agents/simple_openai_agent.py
agentbase/core/__init__.py
agentbase/core/base_protocol.py
agentbase/core/base_protocol_adapter.py
agentbase/core/client.py
agentbase/core/connector.py
agentbase/core/network.py
agentbase/core/system_commands.py
agentbase/launchers/__init__.py
agentbase/launchers/discovery_connector.py
agentbase/launchers/network_launcher.py
agentbase/launchers/terminal_console.py
agentbase/models/__init__.py
agentbase/models/manifest.py
agentbase/models/message_thread.py
agentbase/models/messages.py
agentbase/models/network_config.py
agentbase/models/network_profile.py
agentbase/models/tool.py
agentbase/protocols/__init__.py
agentbase/protocols/communication/__init__.py
agentbase/protocols/communication/simple_messaging/__init__.py
agentbase/protocols/communication/simple_messaging/adapter.py
agentbase/protocols/communication/simple_messaging/protocol.py
agentbase/protocols/discovery/__init__.py
agentbase/protocols/discovery/agent_discovery/__init__.py
agentbase/protocols/discovery/agent_discovery/adapter.py
agentbase/protocols/discovery/agent_discovery/protocol.py
agentbase/utils/__init__.py
agentbase/utils/message_util.py
agentbase/utils/network_discovey.py
agentbase/utils/protocol_loaders.py
agentbase-0.4.0.dist-info/licenses/LICENSE
openagents/__init__.py
openagents/cli.py
openagents/agents/base.py
openagents/agents/runner.py
openagents/agents/simple_openai_agent.py
openagents/core/__init__.py
openagents/core/base_protocol.py
openagents/core/base_protocol_adapter.py
openagents/core/client.py
openagents/core/connector.py
openagents/core/network.py
openagents/core/system_commands.py
openagents/launchers/__init__.py
openagents/launchers/discovery_connector.py
openagents/launchers/network_launcher.py
openagents/launchers/terminal_console.py
openagents/models/__init__.py
openagents/models/manifest.py
openagents/models/message_thread.py
openagents/models/messages.py
agentbase-0.4.0.dist-info/METADATA
agentbase-0.4.0.dist-info/WHEEL
agentbase-0.4.0.dist-info/entry_points.txt
agentbase-0.4.0.dist-info/top_level.txt
agentbase-0.4.0.dist-info/RECORD
